lynx/__init__.py
lynx/api_client.py
lynx/client.py
lynx/controller/__init__.py
lynx/controller/controller.py
lynx/controller/device_controller.py
lynx/controller/edge_app_controller.py
lynx/controller/file_controller.py
lynx/controller/function_controller.py
lynx/controller/installation_controller.py
lynx/controller/installation_info_controller.py
lynx/controller/log_controller.py
lynx/controller/notification_controller.py
lynx/controller/organization_controller.py
lynx/controller/schedule_controller.py
lynx/controller/trace_controller.py
lynx/controller/user_controller.py
lynx/models/__init__.py
lynx/models/constants.py
lynx/models/device.py
lynx/models/edge_app.py
lynx/models/file.py
lynx/models/function.py
lynx/models/installation.py
lynx/models/installation_info.py
lynx/models/log.py
lynx/models/notification.py
lynx/models/organization.py
lynx/models/publisher.py
lynx/models/responses.py
lynx/models/schedule.py
lynx/models/shared.py
lynx/models/trace.py
lynx/models/user.py
iotopen_py_lynx-1.0.7.dist-info/METADATA
iotopen_py_lynx-1.0.7.dist-info/WHEEL
iotopen_py_lynx-1.0.7.dist-info/licenses/LICENSE
iotopen_py_lynx-1.0.7.dist-info/RECORD
