Metadata-Version: 2.3
Name: iotopen-py-lynx
Version: 1.0.7
Summary: A wrapper library for the IoT Open Lynx API
Project-URL: Homepage, https://github.com/IoTOpen/py-lynx
Project-URL: Issues, https://github.com/IoTOpen/py-lynx/issues
Author-email: Jesper Falk <jesper.falk@iotopen.se>
License-File: LICENSE
Keywords: api,iot,iot-open
Classifier: Intended Audience :: Developers
Classifier: License :: OSI Approved :: Apache Software License
Classifier: Operating System :: OS Independent
Classifier: Programming Language :: Python :: 3
Classifier: Topic :: Software Development :: Libraries
Requires-Python: >3.8
Requires-Dist: requests
